nele/__init__.py
nele-0.4.0.dist-info/METADATA
nele-0.4.0.dist-info/WHEEL
nele-0.4.0.dist-info/entry_points.txt
nele-0.4.0.dist-info/top_level.txt
nele-0.4.0.dist-info/RECORD
